{"Bawana Main": {"overstock_info": [], "understock_info": [{"date": "2025-10-25", "forecasted_stock": 974.6893978690871, "explanation": "seasonal trough (weekly component: -67.17 < average 3.27) and downward trend contribution (1036.97 < historical mean 1047.47)"}, {"date": "2025-10-26", "forecasted_stock": 983.9449291639035, "explanation": "seasonal trough (weekly component: -63.69 < average 3.27) and downward trend contribution (1036.95 < historical mean 1047.47)"}, {"date": "2025-11-01", "forecasted_stock": 973.517617092768, "explanation": "seasonal trough (weekly component: -67.17 < average 3.27) and downward trend contribution (1036.82 < historical mean 1047.47)"}, {"date": "2025-11-02", "forecasted_stock": 973.9889677271461, "explanation": "seasonal trough (weekly component: -63.69 < average 3.27) and downward trend contribution (1036.79 < historical mean 1047.47)"}, {"date": "2025-11-08", "forecasted_stock": 969.4646394284491, "explanation": "seasonal trough (weekly component: -67.17 < average 3.27) and downward trend contribution (1036.66 < historical mean 1047.47)"}, {"date": "2025-11-09", "forecasted_stock": 968.8069775406443, "explanation": "seasonal trough (weekly component: -63.69 < average 3.27) and downward trend contribution (1036.64 < historical mean 1047.47)"}, {"date": "2025-11-15", "forecasted_stock": 972.403421927351, "explanation": "seasonal trough (weekly component: -67.17 < average 3.27) and downward trend contribution (1036.51 < historical mean 1047.47)"}, {"date": "2025-11-16", "forecasted_stock": 967.4743402567618, "explanation": "seasonal trough (weekly component: -63.69 < average 3.27) and downward trend contribution (1036.49 < historical mean 1047.47)"}, {"date": "2025-11-22", "forecasted_stock": 969.7873701597917, "explanation": "seasonal trough (weekly component: -67.17 < average 3.27) and downward trend contribution (1036.36 < historical mean 1047.47)"}, {"date": "2025-11-23", "forecasted_stock": 973.156570242465, "explanation": "seasonal trough (weekly component: -63.69 < average 3.27) and downward trend contribution (1036.34 < historical mean 1047.47)"}], "mean_stock": 1047.4683994528043, "over_threshold": 1082.4683994528043, "under_threshold": 987.4683994528043}, "Okhla Depot": {"overstock_info": [], "understock_info": [{"date": "2025-10-25", "forecasted_stock": 674.0261894888839, "explanation": "seasonal trough (weekly component: -72.02 < average 3.54) and downward trend contribution (740.23 < historical mean 746.13)"}, {"date": "2025-10-26", "forecasted_stock": 669.6820361926588, "explanation": "seasonal trough (weekly component: -69.59 < average 3.54) and downward trend contribution (740.22 < historical mean 746.13)"}, {"date": "2025-11-01", "forecasted_stock": 667.5799936389297, "explanation": "seasonal trough (weekly component: -72.02 < average 3.54) and downward trend contribution (740.16 < historical mean 746.13)"}, {"date": "2025-11-02", "forecasted_stock": 674.6779451834204, "explanation": "seasonal trough (weekly component: -69.59 < average 3.54) and downward trend contribution (740.16 < historical mean 746.13)"}, {"date": "2025-11-08", "forecasted_stock": 669.4106588126307, "explanation": "seasonal trough (weekly component: -72.02 < average 3.54) and downward trend contribution (740.10 < historical mean 746.13)"}, {"date": "2025-11-09", "forecasted_stock": 668.4265324239012, "explanation": "seasonal trough (weekly component: -69.59 < average 3.54) and downward trend contribution (740.09 < historical mean 746.13)"}, {"date": "2025-11-15", "forecasted_stock": 669.633052163358, "explanation": "seasonal trough (weekly component: -72.02 < average 3.54) and downward trend contribution (740.03 < historical mean 746.13)"}, {"date": "2025-11-16", "forecasted_stock": 663.6160710185993, "explanation": "seasonal trough (weekly component: -69.59 < average 3.54) and downward trend contribution (740.02 < historical mean 746.13)"}, {"date": "2025-11-22", "forecasted_stock": 666.3150066127324, "explanation": "seasonal trough (weekly component: -72.02 < average 3.54) and downward trend contribution (739.97 < historical mean 746.13)"}, {"date": "2025-11-23", "forecasted_stock": 671.8807957969858, "explanation": "seasonal trough (weekly component: -69.59 < average 3.54) and downward trend contribution (739.96 < historical mean 746.13)"}], "mean_stock": 746.1347469220246, "over_threshold": 781.1347469220246, "under_threshold": 686.1347469220246}, "Narela Hub": {"overstock_info": [{"date": "2025-10-20", "forecasted_stock": 1396.390512105529, "explanation": "seasonal peak (weekly component: 33.00 > average 3.60) and Diwali effect (component: 5.28) and upward trend contribution (1358.11 > historical mean 1347.82)"}, {"date": "2025-10-23", "forecasted_stock": 1387.7333389494734, "explanation": "seasonal peak (weekly component: 26.78 > average 3.60) and Diwali effect (component: 2.78) and upward trend contribution (1358.17 > historical mean 1347.82)"}, {"date": "2025-10-24", "forecasted_stock": 1391.9351322690704, "explanation": "seasonal peak (weekly component: 34.83 > average 3.60) and upward trend contribution (1358.19 > historical mean 1347.82)"}, {"date": "2025-10-27", "forecasted_stock": 1399.657324297837, "explanation": "seasonal peak (weekly component: 33.00 > average 3.60) and Diwali effect (component: 8.40) and upward trend contribution (1358.25 > historical mean 1347.82)"}, {"date": "2025-10-30", "forecasted_stock": 1392.6885073101548, "explanation": "seasonal peak (weekly component: 26.78 > average 3.60) and Diwali effect (component: 7.59) and upward trend contribution (1358.31 > historical mean 1347.82)"}, {"date": "2025-10-31", "forecasted_stock": 1404.7235038963784, "explanation": "seasonal peak (weekly component: 34.83 > average 3.60) and Diwali effect (component: 11.56) and upward trend contribution (1358.33 > historical mean 1347.82)"}, {"date": "2025-11-03", "forecasted_stock": 1389.1127649547336, "explanation": "seasonal peak (weekly component: 33.00 > average 3.60) and upward trend contribution (1358.40 > historical mean 1347.82)"}, {"date": "2025-11-04", "forecasted_stock": 1382.9289206108253, "explanation": "seasonal peak (weekly component: 26.12 > average 3.60) and upward trend contribution (1358.42 > historical mean 1347.82)"}, {"date": "2025-11-07", "forecasted_stock": 1391.7248004908215, "explanation": "seasonal peak (weekly component: 34.83 > average 3.60) and upward trend contribution (1358.48 > historical mean 1347.82)"}, {"date": "2025-11-10", "forecasted_stock": 1395.1828783404246, "explanation": "seasonal peak (weekly component: 33.00 > average 3.60) and Diwali effect (component: 3.64) and upward trend contribution (1358.54 > historical mean 1347.82)"}, {"date": "2025-11-11", "forecasted_stock": 1399.2688099358006, "explanation": "seasonal peak (weekly component: 26.12 > average 3.60) and Diwali effect (component: 14.59) and upward trend contribution (1358.56 > historical mean 1347.82)"}, {"date": "2025-11-12", "forecasted_stock": 1385.6428674725553, "explanation": "seasonal peak (weekly component: 23.18 > average 3.60) and Diwali effect (component: 3.88) and upward trend contribution (1358.58 > historical mean 1347.82)"}, {"date": "2025-11-17", "forecasted_stock": 1389.8365220190315, "explanation": "seasonal peak (weekly component: 33.00 > average 3.60) and upward trend contribution (1358.68 > historical mean 1347.82)"}, {"date": "2025-11-18", "forecasted_stock": 1389.9762168477573, "explanation": "seasonal peak (weekly component: 26.12 > average 3.60) and Diwali effect (component: 5.16) and upward trend contribution (1358.70 > historical mean 1347.82)"}, {"date": "2025-11-19", "forecasted_stock": 1389.7178698301068, "explanation": "seasonal peak (weekly component: 23.18 > average 3.60) and Diwali effect (component: 7.81) and upward trend contribution (1358.72 > historical mean 1347.82)"}, {"date": "2025-11-20", "forecasted_stock": 1385.4527334646143, "explanation": "seasonal peak (weekly component: 26.78 > average 3.60) and upward trend contribution (1358.74 > historical mean 1347.82)"}, {"date": "2025-11-21", "forecasted_stock": 1388.0539242261611, "explanation": "seasonal peak (weekly component: 34.83 > average 3.60) and upward trend contribution (1358.76 > historical mean 1347.82)"}, {"date": "2025-11-24", "forecasted_stock": 1386.8551952079856, "explanation": "seasonal peak (weekly component: 33.00 > average 3.60) and upward trend contribution (1358.82 > historical mean 1347.82)"}, {"date": "2025-11-25", "forecasted_stock": 1384.610412021228, "explanation": "seasonal peak (weekly component: 26.12 > average 3.60) and upward trend contribution (1358.85 > historical mean 1347.82)"}, {"date": "2025-11-26", "forecasted_stock": 1391.555178409731, "explanation": "seasonal peak (weekly component: 23.18 > average 3.60) and Diwali effect (component: 9.50) and upward trend contribution (1358.87 > historical mean 1347.82)"}, {"date": "2025-11-27", "forecasted_stock": 1387.5462654524865, "explanation": "seasonal peak (weekly component: 26.78 > average 3.60) and Diwali effect (component: 1.88) and upward trend contribution (1358.89 > historical mean 1347.82)"}, {"date": "2025-11-28", "forecasted_stock": 1386.3684103197343, "explanation": "seasonal peak (weekly component: 34.83 > average 3.60) and upward trend contribution (1358.91 > historical mean 1347.82)"}], "understock_info": [{"date": "2025-10-25", "forecasted_stock": 1279.942142664728, "explanation": "seasonal trough (weekly component: -73.18 < average 3.60)"}, {"date": "2025-11-02", "forecasted_stock": 1286.7305922278829, "explanation": "seasonal trough (weekly component: -70.74 < average 3.60)"}, {"date": "2025-11-08", "forecasted_stock": 1285.7461087746065, "explanation": "seasonal trough (weekly component: -73.18 < average 3.60)"}, {"date": "2025-11-09", "forecasted_stock": 1283.8198385355638, "explanation": "seasonal trough (weekly component: -70.74 < average 3.60)"}, {"date": "2025-11-15", "forecasted_stock": 1282.2975610033445, "explanation": "seasonal trough (weekly component: -73.18 < average 3.60)"}, {"date": "2025-11-16", "forecasted_stock": 1285.0613345343083, "explanation": "seasonal trough (weekly component: -70.74 < average 3.60)"}, {"date": "2025-11-22", "forecasted_stock": 1286.0328646896312, "explanation": "seasonal trough (weekly component: -73.18 < average 3.60)"}], "mean_stock": 1347.8217510259917, "over_threshold": 1382.8217510259917, "under_threshold": 1287.8217510259917}, "Patparganj Yard": {"overstock_info": [{"date": "2025-10-21", "forecasted_stock": 939.5135131086741, "explanation": "seasonal peak (weekly component: 26.65 > average 3.54) and Diwali effect (component: 10.30) and upward trend contribution (902.57 > historical mean 897.18)"}, {"date": "2025-10-22", "forecasted_stock": 932.7966807433527, "explanation": "seasonal peak (weekly component: 26.81 > average 3.54) and Diwali effect (component: 3.40) and upward trend contribution (902.58 > historical mean 897.18)"}, {"date": "2025-10-24", "forecasted_stock": 933.6405488098266, "explanation": "seasonal peak (weekly component: 29.13 > average 3.54) and Diwali effect (component: 1.90) and upward trend contribution (902.61 > historical mean 897.18)"}, {"date": "2025-10-27", "forecasted_stock": 932.5062014590499, "explanation": "seasonal peak (weekly component: 25.32 > average 3.54) and Diwali effect (component: 4.54) and upward trend contribution (902.64 > historical mean 897.18)"}, {"date": "2025-10-28", "forecasted_stock": 933.7656007088042, "explanation": "seasonal peak (weekly component: 26.65 > average 3.54) and Diwali effect (component: 4.47) and upward trend contribution (902.65 > historical mean 897.18)"}, {"date": "2025-10-30", "forecasted_stock": 934.1787060068549, "explanation": "seasonal peak (weekly component: 33.77 > average 3.54) and upward trend contribution (902.68 > historical mean 897.18)"}, {"date": "2025-11-05", "forecasted_stock": 932.3684088071392, "explanation": "seasonal peak (weekly component: 26.81 > average 3.54) and Diwali effect (component: 2.81) and upward trend contribution (902.74 > historical mean 897.18)"}, {"date": "2025-11-06", "forecasted_stock": 941.0918018943241, "explanation": "seasonal peak (weekly component: 33.77 > average 3.54) and Diwali effect (component: 4.56) and upward trend contribution (902.76 > historical mean 897.18)"}, {"date": "2025-11-07", "forecasted_stock": 933.9564035304584, "explanation": "seasonal peak (weekly component: 29.13 > average 3.54) and Diwali effect (component: 2.06) and upward trend contribution (902.77 > historical mean 897.18)"}, {"date": "2025-11-20", "forecasted_stock": 942.7186887023415, "explanation": "seasonal peak (weekly component: 33.77 > average 3.54) and Diwali effect (component: 6.03) and upward trend contribution (902.92 > historical mean 897.18)"}, {"date": "2025-11-21", "forecasted_stock": 940.7949257507889, "explanation": "seasonal peak (weekly component: 29.13 > average 3.54) and Diwali effect (component: 8.74) and upward trend contribution (902.93 > historical mean 897.18)"}, {"date": "2025-11-24", "forecasted_stock": 934.2794025440929, "explanation": "seasonal peak (weekly component: 25.32 > average 3.54) and Diwali effect (component: 6.00) and upward trend contribution (902.96 > historical mean 897.18)"}, {"date": "2025-11-25", "forecasted_stock": 933.9878198415987, "explanation": "seasonal peak (weekly component: 26.65 > average 3.54) and Diwali effect (component: 4.37) and upward trend contribution (902.97 > historical mean 897.18)"}, {"date": "2025-11-26", "forecasted_stock": 932.998225462891, "explanation": "seasonal peak (weekly component: 26.81 > average 3.54) and Diwali effect (component: 3.20) and upward trend contribution (902.99 > historical mean 897.18)"}, {"date": "2025-11-27", "forecasted_stock": 942.2800092032761, "explanation": "seasonal peak (weekly component: 33.77 > average 3.54) and Diwali effect (component: 5.51) and upward trend contribution (903.00 > historical mean 897.18)"}, {"date": "2025-11-28", "forecasted_stock": 933.3754898964016, "explanation": "seasonal peak (weekly component: 29.13 > average 3.54) and Diwali effect (component: 1.24) and upward trend contribution (903.01 > historical mean 897.18)"}], "understock_info": [{"date": "2025-10-26", "forecasted_stock": 833.4417262078744, "explanation": "seasonal trough (weekly component: -72.14 < average 3.54)"}, {"date": "2025-11-01", "forecasted_stock": 832.9688421798132, "explanation": "seasonal trough (weekly component: -69.54 < average 3.54)"}, {"date": "2025-11-02", "forecasted_stock": 832.0517578423729, "explanation": "seasonal trough (weekly component: -72.14 < average 3.54)"}, {"date": "2025-11-08", "forecasted_stock": 833.0088756205024, "explanation": "seasonal trough (weekly component: -69.54 < average 3.54)"}, {"date": "2025-11-09", "forecasted_stock": 831.2851094842563, "explanation": "seasonal trough (weekly component: -72.14 < average 3.54)"}, {"date": "2025-11-15", "forecasted_stock": 833.1948870895527, "explanation": "seasonal trough (weekly component: -69.54 < average 3.54)"}, {"date": "2025-11-16", "forecasted_stock": 831.4877829750689, "explanation": "seasonal trough (weekly component: -72.14 < average 3.54)"}, {"date": "2025-11-22", "forecasted_stock": 829.8901922550945, "explanation": "seasonal trough (weekly component: -69.54 < average 3.54)"}, {"date": "2025-11-23", "forecasted_stock": 828.316040504979, "explanation": "seasonal trough (weekly component: -72.14 < average 3.54)"}], "mean_stock": 897.1822845417237, "over_threshold": 932.1822845417237, "under_threshold": 837.1822845417237}, "Mayapuri Store": {"overstock_info": [], "understock_info": [{"date": "2025-10-25", "forecasted_stock": 577.475734679692, "explanation": "seasonal trough (weekly component: -73.31 < average 3.70) and downward trend contribution (651.04 < historical mean 668.57)"}, {"date": "2025-10-26", "forecasted_stock": 577.9569367755472, "explanation": "seasonal trough (weekly component: -74.84 < average 3.70) and downward trend contribution (651.00 < historical mean 668.57)"}, {"date": "2025-11-01", "forecasted_stock": 575.3576836791484, "explanation": "seasonal trough (weekly component: -73.31 < average 3.70) and downward trend contribution (650.79 < historical mean 668.57)"}, {"date": "2025-11-02", "forecasted_stock": 577.754515373347, "explanation": "seasonal trough (weekly component: -74.84 < average 3.70) and downward trend contribution (650.75 < historical mean 668.57)"}, {"date": "2025-11-08", "forecasted_stock": 575.1929668565042, "explanation": "seasonal trough (weekly component: -73.31 < average 3.70) and downward trend contribution (650.54 < historical mean 668.57)"}, {"date": "2025-11-09", "forecasted_stock": 578.8327051025547, "explanation": "seasonal trough (weekly component: -74.84 < average 3.70) and downward trend contribution (650.50 < historical mean 668.57)"}, {"date": "2025-11-15", "forecasted_stock": 567.4176477666944, "explanation": "seasonal trough (weekly component: -73.31 < average 3.70) and downward trend contribution (650.29 < historical mean 668.57)"}, {"date": "2025-11-16", "forecasted_stock": 571.5071133162437, "explanation": "seasonal trough (weekly component: -74.84 < average 3.70) and downward trend contribution (650.25 < historical mean 668.57)"}, {"date": "2025-11-22", "forecasted_stock": 583.2137693021568, "explanation": "seasonal trough (weekly component: -73.31 < average 3.70) and downward trend contribution (650.04 < historical mean 668.57)"}, {"date": "2025-11-23", "forecasted_stock": 581.0193737750005, "explanation": "seasonal trough (weekly component: -74.84 < average 3.70) and downward trend contribution (650.00 < historical mean 668.57)"}], "mean_stock": 668.574829001368, "over_threshold": 703.574829001368, "under_threshold": 608.574829001368}, "Kirti Nagar Hub": {"overstock_info": [], "understock_info": [{"date": "2025-10-25", "forecasted_stock": 898.2053157701208, "explanation": "seasonal trough (weekly component: -66.62 < average 3.54) and downward trend contribution (967.62 < historical mean 972.48)"}, {"date": "2025-10-26", "forecasted_stock": 896.1283463414868, "explanation": "seasonal trough (weekly component: -74.95 < average 3.54) and downward trend contribution (967.61 < historical mean 972.48)"}, {"date": "2025-11-01", "forecasted_stock": 899.1025863660021, "explanation": "seasonal trough (weekly component: -66.62 < average 3.54) and downward trend contribution (967.57 < historical mean 972.48)"}, {"date": "2025-11-02", "forecasted_stock": 892.6023864880513, "explanation": "seasonal trough (weekly component: -74.95 < average 3.54) and downward trend contribution (967.56 < historical mean 972.48)"}, {"date": "2025-11-08", "forecasted_stock": 904.0036983306273, "explanation": "seasonal trough (weekly component: -66.62 < average 3.54) and downward trend contribution (967.52 < historical mean 972.48)"}, {"date": "2025-11-09", "forecasted_stock": 893.1686315438777, "explanation": "seasonal trough (weekly component: -74.95 < average 3.54) and downward trend contribution (967.52 < historical mean 972.48)"}, {"date": "2025-11-15", "forecasted_stock": 894.7951162556114, "explanation": "seasonal trough (weekly component: -66.62 < average 3.54) and downward trend contribution (967.48 < historical mean 972.48)"}, {"date": "2025-11-16", "forecasted_stock": 893.6934288867966, "explanation": "seasonal trough (weekly component: -74.95 < average 3.54) and downward trend contribution (967.47 < historical mean 972.48)"}, {"date": "2025-11-22", "forecasted_stock": 900.769407072942, "explanation": "seasonal trough (weekly component: -66.62 < average 3.54) and downward trend contribution (967.43 < historical mean 972.48)"}, {"date": "2025-11-23", "forecasted_stock": 894.5948506616057, "explanation": "seasonal trough (weekly component: -74.95 < average 3.54) and downward trend contribution (967.42 < historical mean 972.48)"}], "mean_stock": 972.4792749658003, "over_threshold": 1007.4792749658003, "under_threshold": 912.4792749658003}, "Sarai Kale Khan Depot": {"overstock_info": [{"date": "2025-10-27", "forecasted_stock": 1069.0447887533653, "explanation": "seasonal peak (weekly component: 29.28 > average 3.58) and Diwali effect (component: 14.32) and upward trend contribution (1025.45 > historical mean 1023.02)"}, {"date": "2025-10-31", "forecasted_stock": 1059.3107166699672, "explanation": "seasonal peak (weekly component: 30.74 > average 3.58) and Diwali effect (component: 3.10) and upward trend contribution (1025.47 > historical mean 1023.02)"}, {"date": "2025-11-04", "forecasted_stock": 1060.6465609398313, "explanation": "seasonal peak (weekly component: 27.77 > average 3.58) and Diwali effect (component: 7.38) and upward trend contribution (1025.50 > historical mean 1023.02)"}, {"date": "2025-11-05", "forecasted_stock": 1061.6346634539282, "explanation": "seasonal peak (weekly component: 27.59 > average 3.58) and Diwali effect (component: 8.55) and upward trend contribution (1025.50 > historical mean 1023.02)"}, {"date": "2025-11-17", "forecasted_stock": 1059.6664467554467, "explanation": "seasonal peak (weekly component: 29.28 > average 3.58) and Diwali effect (component: 4.82) and upward trend contribution (1025.57 > historical mean 1023.02)"}, {"date": "2025-11-26", "forecasted_stock": 1067.0637433628297, "explanation": "seasonal peak (weekly component: 27.59 > average 3.58) and Diwali effect (component: 13.85) and upward trend contribution (1025.63 > historical mean 1023.02)"}, {"date": "2025-11-27", "forecasted_stock": 1061.5892920512526, "explanation": "seasonal peak (weekly component: 27.99 > average 3.58) and Diwali effect (component: 7.97) and upward trend contribution (1025.63 > historical mean 1023.02)"}], "understock_info": [{"date": "2025-10-25", "forecasted_stock": 942.8116033041856, "explanation": "seasonal trough (weekly component: -71.35 < average 3.58)"}, {"date": "2025-10-26", "forecasted_stock": 959.1716563916834, "explanation": "seasonal trough (weekly component: -72.02 < average 3.58)"}, {"date": "2025-11-01", "forecasted_stock": 949.6754055079319, "explanation": "seasonal trough (weekly component: -71.35 < average 3.58)"}, {"date": "2025-11-02", "forecasted_stock": 945.9935711652207, "explanation": "seasonal trough (weekly component: -72.02 < average 3.58)"}, {"date": "2025-11-08", "forecasted_stock": 960.2744571451092, "explanation": "seasonal trough (weekly component: -71.35 < average 3.58)"}, {"date": "2025-11-09", "forecasted_stock": 954.1172949755627, "explanation": "seasonal trough (weekly component: -72.02 < average 3.58)"}, {"date": "2025-11-15", "forecasted_stock": 951.2065704275735, "explanation": "seasonal trough (weekly component: -71.35 < average 3.58)"}, {"date": "2025-11-16", "forecasted_stock": 955.3653187088969, "explanation": "seasonal trough (weekly component: -72.02 < average 3.58)"}, {"date": "2025-11-22", "forecasted_stock": 957.2748090541677, "explanation": "seasonal trough (weekly component: -71.35 < average 3.58)"}, {"date": "2025-11-23", "forecasted_stock": 952.3158346100917, "explanation": "seasonal trough (weekly component: -72.02 < average 3.58)"}], "mean_stock": 1023.0164842681259, "over_threshold": 1058.0164842681259, "under_threshold": 963.0164842681259}}